Metadata-Version: 2.1
Name: odoo14-addon-shopinvader-customer-multi-user-wishlist
Version: 14.0.1.1.0
Summary: Integrate customer multi user and wishlist.
Home-page: https://github.com/shopinvader/odoo-shopinvader
Author: Camptocamp SA
License: AGPL-3
Platform: UNKNOWN
Classifier: Programming Language :: Python
Classifier: Framework :: Odoo
Classifier: Framework :: Odoo :: 14.0
Classifier: License :: OSI Approved :: GNU Affero General Public License v3
Requires-Python: >=3.6
Requires-Dist: odoo14-addon-shopinvader-customer-multi-user
Requires-Dist: odoo14-addon-shopinvader-wishlist
Requires-Dist: odoo (<14.1dev,>=14.0a)
